stonpy/__about__.py
stonpy/__init__.py
stonpy/cli.py
stonpy/completion.py
stonpy/conversion.py
stonpy/core.py
stonpy/model.py
stonpy/sbgn.py
stonpy/utils.py
stonpy/thirdparty/cd2sbgnml/LICENSE
stonpy/thirdparty/cd2sbgnml/cd2sbgnml-0.4.5-app.jar
stonpy/thirdparty/cd2sbgnml/cd2sbgnml.sh
stonpy/thirdparty/cd2sbgnml/sbgnml2cd.sh
stonpy-0.2.1.dist-info/LICENSE
stonpy-0.2.1.dist-info/METADATA
stonpy-0.2.1.dist-info/WHEEL
stonpy-0.2.1.dist-info/entry_points.txt
stonpy-0.2.1.dist-info/top_level.txt
stonpy-0.2.1.dist-info/RECORD
