Metadata-Version: 2.1
Name: stonpy
Version: 0.2.1
Summary: SBGN to Neo4j database
Author: Adrien Rougny
Author-email: Adrien Rougny <adrienrougny@gmail.com>
License: stonpy is free software: you can redistribute it and/or modify
Project-URL: Homepage, https://github.com/adrienrougny/stonpy
Project-URL: Bug Tracker, https://github.com/adrienrougny/stonpy/issues
Classifier: Programming Language :: Python :: 3
Classifier: License :: OSI Approved :: GNU General Public License v3 (GPLv3)
Classifier: Operating System :: OS Independent
Requires-Python: >=3.10
License-File: LICENSE
Requires-Dist: libsbgnpy
Requires-Dist: py2neo
Requires-Dist: rdflib
Requires-Dist: bs4
Requires-Dist: python-magic
Requires-Dist: pandas
Requires-Dist: python-magic-bin ; sys_platform == "win32"
